huobi/__init__.py
huobi/host.py
huobi/coin_swap/__init__.py
huobi/coin_swap/rest/__init__.py
huobi/coin_swap/rest/account.py
huobi/coin_swap/rest/market.py
huobi/coin_swap/rest/order.py
huobi/coin_swap/rest/transfer.py
huobi/coin_swap/rest/trigger_order.py
huobi/coin_swap/ws/__init__.py
huobi/coin_swap/ws/account.py
huobi/coin_swap/ws/index.py
huobi/coin_swap/ws/market.py
huobi/coin_swap/ws/system.py
huobi/futures/__init__.py
huobi/futures/rest/__init__.py
huobi/futures/rest/account.py
huobi/futures/rest/market.py
huobi/futures/rest/order.py
huobi/futures/rest/transfer.py
huobi/futures/rest/trigger_order.py
huobi/futures/ws/__init__.py
huobi/futures/ws/account.py
huobi/futures/ws/index.py
huobi/futures/ws/market.py
huobi/futures/ws/system.py
huobi/linear_swap/__init__.py
huobi/linear_swap/rest/__init__.py
huobi/linear_swap/rest/account.py
huobi/linear_swap/rest/market.py
huobi/linear_swap/rest/order.py
huobi/linear_swap/rest/transfer.py
huobi/linear_swap/rest/trigger_order.py
huobi/linear_swap/ws/__init__.py
huobi/linear_swap/ws/account.py
huobi/linear_swap/ws/index.py
huobi/linear_swap/ws/market.py
huobi/linear_swap/ws/system.py
huobi/utils/__init__.py
huobi/utils/http.py
huobi/utils/logger.py
huobi/utils/ws.py
huobipy-1.0.1.dist-info/LICENSE
huobipy-1.0.1.dist-info/METADATA
huobipy-1.0.1.dist-info/WHEEL
huobipy-1.0.1.dist-info/top_level.txt
huobipy-1.0.1.dist-info/RECORD
