Metadata-Version: 2.1
Name: huobipy
Version: 1.0.1
Summary: huobi api sdk
Home-page: https://github.com/hbdmapi/huobi_sdk_Python
Author: adlong
Author-email: 3140618@163.com
License: UNKNOWN
Project-URL: Bug Tracker, https://github.com/hbdmapi/huobi_sdk_Python/issues
Platform: UNKNOWN
Classifier: Programming Language :: Python :: 3
Classifier: License :: OSI Approved :: MIT License
Classifier: Operating System :: OS Independent
Requires-Python: >=3.6
License-File: LICENSE
